[
  {
    "kind": "write",
    "toolCallId": "call_MLrVHNG57Pk5a5oZSsNirKD0|fc_0b140573c73a94580169eaf8310c7481918a45934c12a3b41c",
    "path": "scripts/verify-m062-s03.test.ts",
    "timestamp": 1777006686731
  },
  {
    "kind": "bash",
    "toolCallId": "call_x9UfRan6vcJKzQXMXUIxGhgB|fc_0b140573c73a94580169eaf86023cc8191a009c01ca08bd805",
    "command": "bun test ./scripts/verify-m062-s03.test.ts ./scripts/verify-m062-s01.test.ts",
    "exitCode": 1,
    "outputSnippet": "bun test v1.3.8 (b64edcb4)\n\nscripts/verify-m062-s03.test.ts:\n(pass) verify-m062-s03 > parse args accepts --json and optional --scenario [10.00ms]\n(pass) verify-m062-s03 > evaluate default matrix reports bounded parity and zero-evidence rejection with stable scenario classifications [3.00ms]\n(pass) verify-m062-s03 > evaluate scenario surfaces invalid contract issues for malformed normalized payloads\n(pass) verify-m062-s03 > evaluate scenario degrades missing remaining scope to truthful uncertaint",
    "timestamp": 1777006688979
  },
  {
    "kind": "edit",
    "toolCallId": "call_7i3msi5HY8iNZggsB1up8hsM|fc_0b140573c73a94580169eaf86483e881919b42d3cfefcb004c",
    "path": "package.json",
    "timestamp": 1777006695411
  },
  {
    "kind": "bash",
    "toolCallId": "call_gTCfWSqSPsH9UUN7MQZKeiSt|fc_0b140573c73a94580169eaf868ea948191923c23282fa4477b",
    "command": "bun test ./scripts/verify-m062-s03.test.ts ./scripts/verify-m062-s01.test.ts",
    "exitCode": 0,
    "outputSnippet": "bun test v1.3.8 (b64edcb4)\n\nscripts/verify-m062-s03.test.ts:\n(pass) verify-m062-s03 > parse args accepts --json and optional --scenario [10.00ms]\n(pass) verify-m062-s03 > evaluate default matrix reports bounded parity and zero-evidence rejection with stable scenario classifications [2.00ms]\n(pass) verify-m062-s03 > evaluate scenario surfaces invalid contract issues for malformed normalized payloads\n(pass) verify-m062-s03 > evaluate scenario degrades missing remaining scope to truthful uncertaint",
    "timestamp": 1777006697728
  },
  {
    "kind": "bash",
    "toolCallId": "call_1wXvvkPLWSczw6zo8WoG0mO3|fc_0b140573c73a94580169eaf86f61a081919f747a6b822cff98",
    "command": "bun run verify:m062:s03 -- --json",
    "exitCode": 0,
    "outputSnippet": "$ bun scripts/verify-m062-s03.ts --json\n{\n  \"command\": \"verify:m062:s03\",\n  \"generated_at\": \"2026-04-24T04:58:23.915Z\",\n  \"scenario_count\": 4,\n  \"success\": true,\n  \"status_code\": \"m062_s03_ok\",\n  \"scenarios\": [\n    {\n      \"scenarioId\": \"timeout-checkpoint\",\n      \"success\": true,\n      \"statusCode\": \"bounded-parity-ok\",\n      \"state\": \"bounded-first-pass\",\n      \"boundedReason\": \"timeout\",\n      \"evidenceSource\": \"checkpoint\",\n      \"boundedCommentEligible\": true,\n      \"boundedCommentRendered\"",
    "timestamp": 1777006703881
  },
  {
    "kind": "bash",
    "toolCallId": "call_E9mpXexxLVZcLJxwYgs25dx3|fc_0b140573c73a94580169eaf87ebbb48191af61d2d557f36ae8",
    "command": "python3 - <<'PY'\nimport subprocess, time, sys\ncmd = ['bun','test','./scripts/verify-m062-s03.test.ts','./scripts/verify-m062-s01.test.ts']\nstart = time.perf_counter()\nproc = subprocess.run(cmd, text=True)\nduration = int((time.perf_counter()-start)*1000)\nprint(f'__EXIT_CODE__={proc.returncode}')\nprint(f'__DURATION_MS__={duration}')\nsys.exit(proc.returncode)\nPY",
    "exitCode": 0,
    "outputSnippet": "bun test v1.3.8 (b64edcb4)\n\nscripts/verify-m062-s03.test.ts:\n(pass) verify-m062-s03 > parse args accepts --json and optional --scenario [11.00ms]\n(pass) verify-m062-s03 > evaluate default matrix reports bounded parity and zero-evidence rejection with stable scenario classifications [4.00ms]\n(pass) verify-m062-s03 > evaluate scenario surfaces invalid contract issues for malformed normalized payloads [1.00ms]\n(pass) verify-m062-s03 > evaluate scenario degrades missing remaining scope to truthful u",
    "timestamp": 1777006719522
  },
  {
    "kind": "bash",
    "toolCallId": "call_Vae93r8xsjEe1Wc46LRcHGmm|fc_0b140573c73a94580169eaf87ebbc481918e3395d0aea853d4",
    "command": "python3 - <<'PY'\nimport subprocess, time, sys\ncmd = ['bun','run','verify:m062:s03','--','--json']\nstart = time.perf_counter()\nproc = subprocess.run(cmd, text=True)\nduration = int((time.perf_counter()-start)*1000)\nprint(f'__EXIT_CODE__={proc.returncode}')\nprint(f'__DURATION_MS__={duration}')\nsys.exit(proc.returncode)\nPY",
    "exitCode": 0,
    "outputSnippet": "$ bun scripts/verify-m062-s03.ts --json\n{\n  \"command\": \"verify:m062:s03\",\n  \"generated_at\": \"2026-04-24T04:58:39.592Z\",\n  \"scenario_count\": 4,\n  \"success\": true,\n  \"status_code\": \"m062_s03_ok\",\n  \"scenarios\": [\n    {\n      \"scenarioId\": \"timeout-checkpoint\",\n      \"success\": true,\n      \"statusCode\": \"bounded-parity-ok\",\n      \"state\": \"bounded-first-pass\",\n      \"boundedReason\": \"timeout\",\n      \"evidenceSource\": \"checkpoint\",\n      \"boundedCommentEligible\": true,\n      \"boundedCommentRendered\"",
    "timestamp": 1777006719522
  }
]
