[
  {
    "kind": "bash",
    "toolCallId": "call_feblkM7Lj1TBy0fOmrlE3Xjx|fc_02b57c9e621d070d0169eb357fb07881918b5359819332b13b",
    "command": "rg --files scripts | rg 'verify-m065.*test|verify-m055-s03.test|verify-m065-s02.test|verify-m064-s03.test'",
    "exitCode": 0,
    "outputSnippet": "scripts/verify-m065.test.ts\nscripts/verify-m064-s03.test.ts\nscripts/verify-m055-s03.test.ts\nscripts/verify-m065-s02.test.ts\n",
    "timestamp": 1777022336035
  },
  {
    "kind": "bash",
    "toolCallId": "call_z4fEkkYr3m6ZJS6MlYwDczoW|fc_02b57c9e621d070d0169eb358f0ce0819180af63d7c3adeab7",
    "command": "find scripts -maxdepth 1 \\( -name 'verify-m065-s03.ts' -o -name 'verify-m065-s03.test.ts' \\) -print",
    "exitCode": 0,
    "outputSnippet": "(no output)",
    "timestamp": 1777022351563
  },
  {
    "kind": "bash",
    "toolCallId": "call_0I09BkBVckQvdLqVyW3zPpEU|fc_02b57c9e621d070d0169eb358f0cf08191966177703f2048eb",
    "command": "rg -n 'verify:m065:s03' package.json docs scripts || true",
    "exitCode": 0,
    "outputSnippet": "(no output)",
    "timestamp": 1777022351563
  },
  {
    "kind": "write",
    "toolCallId": "call_2fAh3QymB8zCM3pf0DSKuyxw|fc_02b57c9e621d070d0169eb35959dd881919ca535e732c17908",
    "path": "scripts/verify-m065-s03.test.ts",
    "timestamp": 1777022401389
  },
  {
    "kind": "bash",
    "toolCallId": "call_oCJLQn2ZvAEltPBUKSk7DmYF|fc_02b57c9e621d070d0169eb35c907a08191933e95f3f7ef5f2e",
    "command": "bun test scripts/verify-m065-s03.test.ts",
    "exitCode": 1,
    "outputSnippet": "bun test v1.3.8 (b64edcb4)\n\nscripts/verify-m065-s03.test.ts:\n\n# Unhandled error between tests\n-------------------------------\nerror: Cannot find module './verify-m065-s03.ts' from '/home/keith/src/kodiai/scripts/verify-m065-s03.test.ts'\n-------------------------------\n\n\n 0 pass\n 1 fail\n 1 error\nRan 1 test across 1 file. [79.00ms]\n\n\nCommand exited with code 1",
    "timestamp": 1777022409992
  },
  {
    "kind": "write",
    "toolCallId": "call_PQAg1xQ9QTbLjgJi8aO26uhV|fc_02b57c9e621d070d0169eb35d018888191ac4f4eb7605a0c0d",
    "path": "scripts/verify-m065-s03.ts",
    "timestamp": 1777022499375
  },
  {
    "kind": "edit",
    "toolCallId": "call_oof6q5hQ9SzgfmgJBBWgAHAp|fc_02b57c9e621d070d0169eb3629d73881918a184148275987b5",
    "path": "package.json",
    "timestamp": 1777022506742
  },
  {
    "kind": "bash",
    "toolCallId": "call_Fqp6rkyN5Cxv0PpYEfDOIdzk|fc_02b57c9e621d070d0169eb3630f578819180d5fd0c24f42814",
    "command": "bun test scripts/verify-m065-s03.test.ts",
    "exitCode": 0,
    "outputSnippet": "bun test v1.3.8 (b64edcb4)\n\nscripts/verify-m065-s03.test.ts:\n(pass) verify-m065-s03 > parse args accepts --json and --help and rejects unknown flags\n(pass) verify-m065-s03 > exports stable check ids and preserves nested regression proof/report keys [1.00ms]\n(pass) verify-m065-s03 > fails with stable status codes for malformed nested proof, missing runbook, unresolved commands, and missing package wiring\n(pass) verify-m065-s03 > package.json wires verify:m065:s03 to the dedicated verifier script\n",
    "timestamp": 1777022513440
  },
  {
    "kind": "bash",
    "toolCallId": "call_SFhvX9zdZjTcd8MyxMTvTcEs|fc_02b57c9e621d070d0169eb363b65c88191ab64110ee7090795",
    "command": "bun test scripts/verify-m065-s03.test.ts --filter \"parse args\"",
    "exitCode": 0,
    "outputSnippet": "bun test v1.3.8 (b64edcb4)\n\nscripts/verify-m065-s03.test.ts:\n(pass) verify-m065-s03 > parse args accepts --json and --help and rejects unknown flags\n(pass) verify-m065-s03 > exports stable check ids and preserves nested regression proof/report keys [2.00ms]\n(pass) verify-m065-s03 > fails with stable status codes for malformed nested proof, missing runbook, unresolved commands, and missing package wiring\n(pass) verify-m065-s03 > package.json wires verify:m065:s03 to the dedicated verifier script ",
    "timestamp": 1777022524013
  },
  {
    "kind": "bash",
    "toolCallId": "call_OzI7Vyrv625TTJkmoJwbI7pp|fc_02b57c9e621d070d0169eb363b65d88191a1e31c7ba3ce8eea",
    "command": "bun run verify:m065:s03 -- --help",
    "exitCode": 0,
    "outputSnippet": "$ bun scripts/verify-m065-s03.ts --help\nUsage: bun run verify:m065:s03 -- [--json]\n\nWraps authoritative verify:m061:regression evidence and pins operator rerun packaging seams for M065 S03.\n\nOptions:\n  --json       Print machine-readable JSON output\n  --help       Show this help\n",
    "timestamp": 1777022524013
  },
  {
    "kind": "bash",
    "toolCallId": "call_ZjXpoFiwFtbKN3plipnbIfB8|fc_02b57c9e621d070d0169eb3644a5408191b0c838db6837e35a",
    "command": "python3 - <<'PY'\nimport subprocess, time\ncommands = [\n  [\"bun\",\"test\",\"scripts/verify-m065-s03.test.ts\"],\n  [\"bun\",\"test\",\"scripts/verify-m065-s03.test.ts\",\"--filter\",\"parse args\"],\n  [\"bun\",\"run\",\"verify:m065:s03\",\"--\",\"--help\"],\n]\nfor cmd in commands:\n    start = time.time()\n    p = subprocess.run(cmd, capture_output=True, text=True)\n    dur = int((time.time() - start)*1000)\n    print('CMD:', ' '.join(cmd))\n    print('EXIT:', p.returncode)\n    print('DURATION_MS:', dur)\n    print('STDOUT_BEGIN')\n    print(p.stdout.rstrip())\n    print('STDOUT_END')\n    if p.stderr:\n        print('STDERR_BEGIN')\n        print(p.stderr.rstrip())\n        print('STDERR_END')\n    print('---')\nPY",
    "exitCode": 0,
    "outputSnippet": "CMD: bun test scripts/verify-m065-s03.test.ts\nEXIT: 0\nDURATION_MS: 105\nSTDOUT_BEGIN\nbun test v1.3.8 (b64edcb4)\nSTDOUT_END\nSTDERR_BEGIN\n\nscripts/verify-m065-s03.test.ts:\n(pass) verify-m065-s03 > parse args accepts --json and --help and rejects unknown flags\n(pass) verify-m065-s03 > exports stable check ids and preserves nested regression proof/report keys [1.00ms]\n(pass) verify-m065-s03 > fails with stable status codes for malformed nested proof, missing runbook, unresolved commands, and missing ",
    "timestamp": 1777022536141
  }
]
