{
  "schemaVersion": 1,
  "taskId": "T03",
  "unitId": "M048/S01/T03",
  "timestamp": 1776039341055,
  "passed": false,
  "discoverySource": "task-plan",
  "checks": [
    {
      "command": "bun test ./src/review-audit/phase-timing-evidence.test.ts ./scripts/verify-m048-s01.test.ts",
      "exitCode": 0,
      "durationMs": 27,
      "verdict": "pass"
    },
    {
      "command": "bun run verify:m048:s01 -- --review-output-key \"$REVIEW_OUTPUT_KEY\" --json",
      "exitCode": 1,
      "durationMs": 33,
      "verdict": "fail"
    }
  ],
  "retryAttempt": 1,
  "maxRetries": 2
}
